illallangi/rdf/__init__.py
illallangi/rdf/__version__.py
illallangi/rdf/tools.py
illallangi/rdf/adapters/__init__.py
illallangi/rdf/adapters/aviation.py
illallangi/rdf/adapters/education.py
illallangi/rdf/adapters/residential.py
illallangi/rdf/client/__init__.py
illallangi/rdf/client/aircraft.py
illallangi/rdf/client/airline.py
illallangi/rdf/client/airport.py
illallangi/rdf/client/course.py
illallangi/rdf/client/manufacturer.py
illallangi/rdf/client/residence.py
illallangi/rdf/converters/__init__.py
illallangi/rdf/converters/partial_date.py
illallangi/rdf/diffsyncmodels/__init__.py
illallangi/rdf/diffsyncmodels/airline.py
illallangi/rdf/diffsyncmodels/airport.py
illallangi/rdf/diffsyncmodels/course.py
illallangi/rdf/diffsyncmodels/residence.py
illallangi/rdf/models/__init__.py
illallangi/rdf/models/aircraft.py
illallangi/rdf/models/airline.py
illallangi/rdf/models/airport.py
illallangi/rdf/models/alliance.py
illallangi/rdf/models/course.py
illallangi/rdf/models/manufacturer.py
illallangi/rdf/models/residence.py
illallangi_rdf-0.5.0.dist-info/METADATA
illallangi_rdf-0.5.0.dist-info/WHEEL
illallangi_rdf-0.5.0.dist-info/entry_points.txt
illallangi_rdf-0.5.0.dist-info/licenses/LICENSE
illallangi_rdf-0.5.0.dist-info/RECORD
