Metadata-Version: 2.3
Name: illallangi-rdf
Version: 0.5.0
Summary: A collection of command line tools to interact with RDF.
Project-URL: Homepage, https://github.com/illallangi/python-rdf
Project-URL: Repository, https://github.com/illallangi/python-rdf.git
Project-URL: Issues, https://github.com/illallangi/python-rdf/issues
Project-URL: Changelog, https://github.com/illallangi/python-rdf/blob/master/CHANGELOG.md
Author-email: Andrew Cole <andrew.cole@illallangi.com>
Maintainer-email: Andrew Cole <andrew.cole@illallangi.com>
License: MIT License
License-File: LICENSE
Keywords: cli,rdf,tools
Classifier: Development Status :: 3 - Alpha
Classifier: Intended Audience :: Developers
Classifier: License :: OSI Approved :: MIT License
Classifier: Programming Language :: Python :: 3.12
Requires-Python: >=3.10.1
Requires-Dist: attrs>=24.2.0
Requires-Dist: cattrs>=24.1.2
Requires-Dist: click>=8.1.7
Requires-Dist: diffsync>=2.0.0
Requires-Dist: django-partial-date>=1.3.2
Requires-Dist: orjson>=3.10.7
Requires-Dist: python-dotenv>=1.0.1
Requires-Dist: rdflib>=7.0.0
Requires-Dist: requests>=2.32.3
Requires-Dist: tabulate>=0.9.0
